setup.py
micropython_microqueue.egg-info/PKG-INFO
micropython_microqueue.egg-info/SOURCES.txt
micropython_microqueue.egg-info/dependency_links.txt
micropython_microqueue.egg-info/requires.txt
micropython_microqueue.egg-info/top_level.txt
micropython_microqueue.egg-info/zip-safe
microqueue/__init__.py
microqueue/queue.py