Metadata-Version: 1.0
Name: micropython-microqueue
Version: 0.0.10
Summary: Simple redis queue for MicroPython
Home-page: https://github.com/dhubbard/micropython-microqueue
Author: Dwight Hubbard
Author-email: dwight@dwighthubbard.com
License: MIT
Platform: UNKNOWN
